jumpstarter_cli_common/__init__.py
jumpstarter_cli_common/alias.py
jumpstarter_cli_common/blocking.py
jumpstarter_cli_common/config.py
jumpstarter_cli_common/exceptions.py
jumpstarter_cli_common/oidc.py
jumpstarter_cli_common/opt.py
jumpstarter_cli_common/print.py
jumpstarter_cli_common/py.typed
jumpstarter_cli_common/signal.py
jumpstarter_cli_common/version.py
jumpstarter_cli_common-0.7.4.dist-info/METADATA
jumpstarter_cli_common-0.7.4.dist-info/WHEEL
jumpstarter_cli_common-0.7.4.dist-info/RECORD
