Metadata-Version: 2.4
Name: jumpstarter-cli-common
Version: 0.7.4
Project-URL: Homepage, https://jumpstarter.dev
Project-URL: source_archive, https://github.com/jumpstarter-dev/repo/archive/c5d38de69eadbb8eb0388bcfe3430a679fff0059.zip
Author-email: Kirk Brauer <kbrauer@hatci.com>
License-Expression: Apache-2.0
Requires-Python: >=3.11
Requires-Dist: authlib>=1.4.1
Requires-Dist: click>=8.1.7.2
Requires-Dist: joserfc>=1.0.3
Requires-Dist: jumpstarter==0.7.4
Requires-Dist: pydantic>=2.8.2
Requires-Dist: rich>=14.0.0
Requires-Dist: truststore>=0.10.1
Requires-Dist: yarl>=1.18.3
